d0/__init__.py
d0/pLogger.py
d0/pMgr.py
d0/qMgr.py
d0/qSaver.py
d0/util.py
duo_tools-0.0.2.dist-info/LICENSE
duo_tools-0.0.2.dist-info/METADATA
duo_tools-0.0.2.dist-info/WHEEL
duo_tools-0.0.2.dist-info/top_level.txt
duo_tools-0.0.2.dist-info/RECORD
