Metadata-Version: 2.1
Name: duo-tools
Version: 0.0.2
Summary: Chen Duo's personal tool
Home-page: https://github.com/cheduo/duo_tools
Author: Chen Duo
Author-email: cdsjtu@gmail.com
License: UNKNOWN
Platform: UNKNOWN
Classifier: Programming Language :: Python :: 3
Classifier: License :: OSI Approved :: MIT License
Classifier: Operating System :: OS Independent
Requires-Python: >=3.6
License-File: LICENSE
Requires-Dist: qpython
